pycti_mcp/__init__.py
pycti_mcp/cli.py
pycti_mcp/mcp_server_octi.py
pycti_mcp/pycti_tools/__init__.py
pycti_mcp/pycti_tools/lookup_adversary.py
pycti_mcp/pycti_tools/lookup_observables.py
pycti_mcp/pycti_tools/lookup_reports.py
pycti_mcp-0.2.0.dist-info/licenses/LICENSE
pycti_mcp-0.2.0.dist-info/WHEEL
pycti_mcp-0.2.0.dist-info/entry_points.txt
pycti_mcp-0.2.0.dist-info/METADATA
pycti_mcp-0.2.0.dist-info/RECORD
