Metadata-Version: 2.4
Name: pycti-mcp
Version: 0.2.0
Summary: Model Context Protocol (MCP) Server for OpenCTI
Author: Coleman Kane
Author-email: Coleman Kane <ckane@colemankane.org>
License-Expression: MIT
License-File: LICENSE
Requires-Dist: fastmcp>=2.10.1
Requires-Dist: mcp[cli]>=1.6.0
Requires-Dist: pycti>=6.7.2
Requires-Python: >=3.12
Project-URL: Homepage, https://github.com/ckane/pycti-mcp
Project-URL: Issue Tracker, https://github.com/ckane/pycti-mcp/issues
Project-URL: Repository, https://github.com/ckane/pycti-mcp
